LICENSE
README.md
setup.py
filelock4s/__init__.py
filelock4s/rw_lock_pool.py
filelock4s/semaphore_lock_pool.py
filelock4s/shared_file_lock.py
filelock4s/user_pool.py
filelock4s/worker_lock_pool.py
filelock4s.egg-info/PKG-INFO
filelock4s.egg-info/SOURCES.txt
filelock4s.egg-info/dependency_links.txt
filelock4s.egg-info/not-zip-safe
filelock4s.egg-info/requires.txt
filelock4s.egg-info/top_level.txt