Metadata-Version: 2.1
Name: filelock4s
Version: 1.0.0
Summary: single shared lock pool manage by filelock
Home-page: https://github.com/meanstrong/filelock4s
Author: pengmingqiang
Author-email: rockypengchina@outlook.com
Maintainer: pengmingqiang
Maintainer-email: rockypengchina@outlook.com
License: Apache 2.0
Platform: any
Classifier: Programming Language :: Python :: 3.9
Classifier: Operating System :: OS Independent
License-File: LICENSE
